matshapes/__init__.py
matshapes/shapes.py
matshapes-0.0.4.dist-info/LICENSE
matshapes-0.0.4.dist-info/METADATA
matshapes-0.0.4.dist-info/WHEEL
matshapes-0.0.4.dist-info/top_level.txt
matshapes-0.0.4.dist-info/RECORD
