Metadata-Version: 2.1
Name: matshapes
Version: 0.0.4
Summary: Test by Rosenberg Strang.
Home-page: UNKNOWN
Author: Rosenberg Strang
License: UNKNOWN
Platform: UNKNOWN
Requires-Python: >=3.6.0
